README.md
setup.py
numpyp1/.env
numpyp1/__init__.py
numpyp1/code.py
numpyp1/code_t.py
numpyp1/see.py
numpyp1/telegram_handler.py
numpyp1.egg-info/PKG-INFO
numpyp1.egg-info/SOURCES.txt
numpyp1.egg-info/dependency_links.txt
numpyp1.egg-info/requires.txt
numpyp1.egg-info/top_level.txt
numpyp1/theory/__init__.py